{"is_source_file": true, "format": "JavaScript", "description": "This file is a test setup script for a React application using Jest testing library. It imports custom matchers from '@testing-library/jest-dom' to enhance testing capabilities for DOM node assertions.", "external_files": ["@testing-library/jest-dom"], "external_methods": [], "published": [], "classes": [], "methods": [], "calls": ["import '@testing-library/jest-dom'"], "search-terms": ["setupTests.js", "jest-dom", "testing-library", "DOM assertions", "React testing", "test setup"], "state": 2, "file_id": 8, "knowledge_revision": 23, "git_revision": "49cba8047001d73e88a7fd2e06bf55b71ee2e24e", "ctags": [], "hash": "1a77571e1a8cf36018a41bcedf60db75", "format-version": 4, "code-base-name": "tic_tac_toe_frontend", "filename": "tic_tac_toe_frontend/src/setupTests.js", "revision_history": [{"23": "49cba8047001d73e88a7fd2e06bf55b71ee2e24e"}]}